drf_swagger_customization/__init__.py
drf_swagger_customization/apps.py
drf_swagger_customization/renderers.py
drf_swagger_customization/utils.py
drf_swagger_customization/views.py
drf_swagger_customization/static/css/drf_swagger_customization.css
drf_swagger_customization/static/js/drf_swagger_customization.js
drf_swagger_customization/templates/drf_swagger_customization/base.html
drf_swagger_customization-0.1.5.dist-info/DESCRIPTION.rst
drf_swagger_customization-0.1.5.dist-info/METADATA
drf_swagger_customization-0.1.5.dist-info/RECORD
drf_swagger_customization-0.1.5.dist-info/WHEEL
drf_swagger_customization-0.1.5.dist-info/metadata.json
drf_swagger_customization-0.1.5.dist-info/top_level.txt
