Metadata-Version: 2.0
Name: drf-swagger-customization
Version: 0.1.5
Summary: This is a django app which you can modify and improve your autogenerated swagger documentation from your drf API.
Home-page: https://github.com/androiz/drf-swagger-customization
Author: Andres Rojano Ruiz
Author-email: androiz10@gmail.com
License: MIT
Keywords: drf-swagger-customization
Platform: UNKNOWN
Classifier: Development Status :: 3 - Alpha
Classifier: Framework :: Django
Classifier: Framework :: Django :: 1.8
Classifier: Framework :: Django :: 1.9
Classifier: Framework :: Django :: 1.10
Classifier: Intended Audience :: Developers
Classifier: License :: OSI Approved :: BSD License
Classifier: Natural Language :: English
Classifier: Programming Language :: Python :: 2
Classifier: Programming Language :: Python :: 2.7
Classifier: Programming Language :: Python :: 3
Classifier: Programming Language :: Python :: 3.3
Classifier: Programming Language :: Python :: 3.4
Classifier: Programming Language :: Python :: 3.5
Requires-Dist: django-rest-swagger (>=2.0.5)
Requires-Dist: djangorestframework (>=3.6.3)
